Metadata-Version: 2.1
Name: odoo12-addon-l10n_es_extra_data
Version: 12.0.4.0.0
Summary: Datos extra de la localización española
Home-page: https://github.com/OCA/l10n-spain
Author: Trey (www.trey.es), Odoo Community Association (OCA)
Author-email: support@odoo-community.org
License: AGPL-3
Classifier: Programming Language :: Python
Classifier: Framework :: Odoo
Classifier: Framework :: Odoo :: 12.0
Classifier: License :: OSI Approved :: GNU Affero General Public License v3
Requires-Python: >=3.5
Requires-Dist: odoo<12.1dev,>=12.0a
